<?xml version="1.0" encoding="UTF-8"?>
<presentation xmlns="http://jason-redding.com/xsd/resume"
	xmlns:xsi="http://www.w3.org/2001/XMLSchema-instance"
	xmlns:h="http://www.w3.org/1999/xhtml"
	xmlns:r="http://jason-redding.com/xsd/resume"
	xsi:schemaLocation="http://jason-redding.com/xsd/resume xsd/resume.xsd">
	<author layout="split">
		<name/>
		<seeking/>
		<!--<email label="Email"/>-->
		<!--<phone label="Cell"/>-->
		<split/>
		<clearance label="Clearance"/>
		<address label="Residence"/>
		<!--<willing-to-travel label="% Willing to Travel"/>-->
		<willing-to-relocate label="Willing to Relocate"/>
		<last-updated label="Last Updated" format="M/d/yyyy"/>
	</author>
	<blurb/>
	<!--<description/>-->
	<!--<competencies/>-->
	<!--<certifications/>-->
	<skills/>
	<employers projects="hide"/>
</presentation>